{
  "$schema": "https://developer.microsoft.com/json-schemas/fabric/item/report/definition/visualContainer/2.6.0/schema.json",
  "name": "9d643b0aebf38f56ec0b",
  "position": {
    "x": 1060.3339517625232,
    "y": 434.582560296846,
    "z": 0,
    "height": 86.679035250463826,
    "width": 189.98144712430428,
    "tabOrder": 4000
  },
  "visual": {
    "visualType": "card",
    "autoSelectVisualType": true,
    "query": {
      "queryState": {
        "Values": {
          "projections": [
            {
              "field": {
                "Measure": {
                  "Expression": {
                    "SourceRef": {
                      "Entity": "Dim_Date"
                    }
                  },
                  "Property": "Test Count"
                }
              },
              "queryRef": "Dim_Date.Test Count",
              "nativeQueryRef": "Test Count"
            }
          ]
        }
      }
    },
    "drillFilterOtherVisuals": true
  }
}